scad_export/__init__.py
scad_export/export.py
scad_export/export_config.py
scad_export/exportable.py
scad_export/user_input.py
scad_export-1.7.dist-info/METADATA
scad_export-1.7.dist-info/WHEEL
scad_export-1.7.dist-info/licenses/LICENSE.md
scad_export-1.7.dist-info/RECORD
