Metadata-Version: 2.4
Name: scad_export
Version: 1.7
Summary: Export script for SCAD files
Project-URL: Homepage, https://github.com/CharlesLenk/scad_export
Project-URL: Issues, https://github.com/CharlesLenk/scad_export/issues
Author-email: Charles Lenk <lenk.charles@gmail.com>
License-Expression: MIT
License-File: LICENSE.md
Classifier: Operating System :: OS Independent
Classifier: Programming Language :: Python :: 3
Requires-Python: >=3.13
